{"lang": "hi", "source_path": "/data/oikantik_sarvam_ai/wiki-data/economy/html/hi/Adani_Green_hi.html", "page_url": "https://hi.wikipedia.org/wiki/%E0%A4%85%E0%A4%A6%E0%A4%BE%E0%A4%A3%E0%A5%80_%E0%A4%97%E0%A5%8D%E0%A4%B0%E0%A5%80%E0%A4%A8_%E0%A4%87%E0%A4%A8%E0%A4%B0%E0%A5%8D%E0%A4%9C%E0%A5%80", "title": "अदाणी ग्रीन इनर्जी", "blocks": [{"type": "table", "md": "*अदाणी ग्रीन इनर्जी Adani Green Energy Limited*\n\n| Col1 |\n| --- |\n| [[File:Aerial view of कामुती सौर ऊर्जा परियोजना |frameless|upright=1]] |\n| कंपनी प्रकार |\n| कारोबारी रूप |\n| आई.एस.आई.एन |\n| उद्योग |\n| स्थापित |\n| स्थापक |\n| मुख्यालय |\n| सेवा क्षेत्र |\n| प्रमुख लोग |\n| उत्पाद |\n| आय |\n| परिचालन आय |\n| शुद्ध आय |\n| कुल संपत्ति |\n| कुल हिस्सेदारी |\n| मालिक |\n| मूल कंपनी |\n| वेबसाइट |\n| टिप्पणियाँ / संदर्भ [ 4 ] |\n", "section": []}, {"type": "text", "text": "अदाणी ग्रीन इनर्जी लिमिटेड (एजीईएल) एक भारतीय नवीकरणीय ऊर्जा कंपनी है जिसका मुख्यालय गुजरात की राजधानी अहमदाबाद में है। [ 5 ] यह अदाणी समूह की कम्पनी है। यह कंपनी कामुथी सौर ऊर्जा परियोजना का संचालन करती है, जो दुनिया के सबसे बड़े सौर फोटोवोल्टिक संयंत्रों में से एक है। [ 6 ] [ 7 ] [ 8 ] मई २०२३ में अदाणी ग्रीन इनर्जी द्वारा स्थापित पवन ऊर्जा की कुल क्षमता १ जीगावाट से अधिक हो गयी।", "section": []}, {"type": "text", "text": "इस कम्पनी की स्थापना २३ जनवरी २०२३ को की गयी थी।", "section": []}]}